LICENSE
MANIFEST.in
README.rst
requirements.txt
setup.cfg
setup.py
ckanext/__init__.py
ckanext/terria_view/__init__.py
ckanext/terria_view/plugin.py
ckanext/terria_view/templates/terria.html
ckanext/terria_view/templates/terria_instance_url.html
ckanext/terria_view/tests/__init__.py
ckanext/terria_view/tests/test_plugin.py
ckanext_terria_view.egg-info/PKG-INFO
ckanext_terria_view.egg-info/SOURCES.txt
ckanext_terria_view.egg-info/dependency_links.txt
ckanext_terria_view.egg-info/entry_points.txt
ckanext_terria_view.egg-info/namespace_packages.txt
ckanext_terria_view.egg-info/top_level.txt