Metadata-Version: 1.1
Name: ckanext-terria-view
Version: 0.0.1
Summary: Preview TerriaJS Supported data in a TerriaJS instance.
Home-page: https://github.com/terriajs/ckanext-terria_view
Author: Nahid Akbar
Author-email: nahid.akbar@data61.csiro.au
License: AGPL
Keywords: CKAN terriajs
Platform: UNKNOWN
Classifier: Development Status :: 4 - Beta
Classifier: License :: OSI Approved :: GNU Affero General Public License v3 or later (AGPLv3+)
Classifier: Programming Language :: Python :: 2.7
